docs/CHANGELOG.rst
docs/CONTRIBUTING.rst
docs/LICENSE.txt
commands/__init__.py
commands/compare.py
commands/compare_accuracy.py
commands/compare_info.py
commands/compare_step_speed.py
commands/create.py
commands/download.py
commands/info.py
commands/predict.py
commands/shared.py
commands/test.py
commands/train.py
dependencies/__init__.py
dependencies/core.py
dependencies/datatypes.py
dependencies/fancy.py
features/__init__.py
features/comparer/comparer.py
features/torchvision_downloader/torchvision_downloader.py
features/trainer/trainer.py
libs/__init__.py
libs/colorized_diff.py
libs/get_args_kwargs_from_string.py
libs/image_transforms.py
libs/pad_to_size_transform.py
libs/prettify_comparer.py
libs/pretty_train.py
libs/shape_transforms.py
libs/sizeof_formated.py
libs/un_labeled_image_dataset.py
main.py
modules/__init__.py
modules/models/__init__.py
modules/models/abs_module.py
modules/models/alexnet.py
modules/models/basic.py
modules/models/basic_conv.py
modules/models/dummy.py
modules/models/elemental.py
modules/models/lenet5.py
modules/models/mnasnet.py
modules/models/squeezenet.py
modules/transforms/__init__.py
modules/transforms/flowers.py
modules/transforms/flowers_unshaped.py
modules/transforms/img_small.py
modules/transforms/mnist.py
modules/transforms/mnist_4D.py
alicia-0.3.0.dist-info/METADATA
alicia-0.3.0.dist-info/WHEEL
alicia-0.3.0.dist-info/entry_points.txt
alicia-0.3.0.dist-info/RECORD
