Metadata-Version: 2.1
Name: alicia
Version: 0.3.0
Summary: A CLI to download, create, modify, train, test, predict and compare an image classifiers.
Home-page: https://pypi.org/project/alicia/
License: MIT
Keywords: neural-network,classifiers,image,machine-learning,performance,diff,compare,ai,torch,torchvision
Author: aemonge
Author-email: andres@aemonge.com
Requires-Python: >=3.10,<3.12
Classifier: Development Status :: 3 - Alpha
Classifier: Environment :: Console
Classifier: Intended Audience :: Developers
Classifier: License :: OSI Approved :: MIT License
Classifier: Natural Language :: English
Classifier: Operating System :: OS Independent
Classifier: Programming Language :: Python :: 3
Classifier: Programming Language :: Python :: 3.10
Classifier: Programming Language :: Python :: 3.11
Classifier: Programming Language :: Python :: 3.10
Classifier: Topic :: Scientific/Engineering :: Artificial Intelligence
Requires-Dist: better-abc (>=0.0.3,<0.0.4)
Requires-Dist: click (>=8.1,<9.0)
Requires-Dist: loading-display (>=0.2,<0.3)
Requires-Dist: matplotlib (>=3.6,<4.0)
Requires-Dist: numpy (>=1.24,<2.0)
Requires-Dist: pillow (>=9.4,<10.0)
Requires-Dist: plotext (>=5.2,<6.0)
Requires-Dist: pympler (>=1.0.1,<2.0.0)
Requires-Dist: scipy (>=1.10,<2.0)
Requires-Dist: termcolor (>=2.2,<3.0)
Requires-Dist: torch (>=1.13,<2.0)
Requires-Dist: torchvision (>=0.14,<0.15)
Requires-Dist: wcmatch (>=8.4,<9.0)
Project-URL: Documentation, https://pypi.org/project/alicia/docs
Project-URL: Repository, https://github.com/aemonge/alicia
